[{"symbol": "HDFCBANK", "instrument": "Stock Futures", "instrumentType": "FUTSTK", "expiryDate": "30-Dec-2025", "ltp": 994.9, "prevClose": 1001.6, "pChange": -0.67, "latestOI": 359256, "prevOI": 362161, "changeInOI": -2905, "pChangeInOI": -0.8, "volume": 28545, "turnover": 156166.98322, "underlyingValue": 990.4, "category": "Slide-in-OI-Slide", "type": "SS", "abs_pChange": 0.67, "volume_score": "Very High"}, {"symbol": "INFY", "instrument": "Stock Futures", "instrumentType": "FUTSTK", "expiryDate": "30-Dec-2025", "ltp": 1591.8, "prevClose": 1604.0, "pChange": -0.76, "latestOI": 162645, "prevOI": 164800, "changeInOI": -2155, "pChangeInOI": -1.31, "volume": 10158, "turnover": 64913.27688, "underlyingValue": 1584.8, "category": "Slide-in-OI-Slide", "type": "SS", "abs_pChange": 0.76, "volume_score": "High"}, {"symbol": "M&M", "instrument": "Stock Futures", "instrumentType": "FUTSTK", "expiryDate": "30-Dec-2025", "ltp": 3640.3, "prevClose": 3657.5, "pChange": -0.47, "latestOI": 89539, "prevOI": 91535, "changeInOI": -1996, "pChangeInOI": -2.18, "volume": 8956, "turnover": 65712.50056, "underlyingValue": 3633.4, "category": "Slide-in-OI-Slide", "type": "SS", "abs_pChange": 0.47, "volume_score": "High"}, {"symbol": "TCS", "instrument": "Stock Futures", "instrumentType": "FUTSTK", "expiryDate": "30-Dec-2025", "ltp": 3194.5, "prevClose": 3217.4, "pChange": -0.71, "latestOI": 139188, "prevOI": 141155, "changeInOI": -1967, "pChangeInOI": -1.39, "volume": 9139, "turnover": 51227.65921, "underlyingValue": 3185.0, "category": "Slide-in-OI-Slide", "type": "SS", "abs_pChange": 0.71, "volume_score": "High"}, {"symbol": "SBIN", "instrument": "Stock Futures", "instrumentType": "FUTSTK", "expiryDate": "30-Dec-2025", "ltp": 960.3, "prevClose": 963.0, "pChange": -0.28, "latestOI": 93576, "prevOI": 95407, "changeInOI": -1831, "pChangeInOI": -1.92, "volume": 10002, "turnover": 72097.66665, "underlyingValue": 958.0, "category": "Slide-in-OI-Slide", "type": "SS", "abs_pChange": 0.28, "volume_score": "High"}, {"symbol": "BAJAJFINSV", "instrument": "Stock Futures", "instrumentType": "FUTSTK", "expiryDate": "30-Dec-2025", "ltp": 2071.4, "prevClose": 2074.6, "pChange": -0.15, "latestOI": 71635, "prevOI": 73377, "changeInOI": -1742, "pChangeInOI": -2.37, "volume": 5659, "turnover": 29500.367, "underlyingValue": 2060.0, "category": "Slide-in-OI-Slide", "type": "SS", "abs_pChange": 0.15, "volume_score": "Medium"}, {"symbol": "BAJFINANCE", "instrument": "Stock Futures", "instrumentType": "FUTSTK", "expiryDate": "30-Dec-2025", "ltp": 1015.0, "prevClose": 1022.1, "pChange": -0.69, "latestOI": 111168, "prevOI": 112838, "changeInOI": -1670, "pChangeInOI": -1.48, "volume": 7384, "turnover": 56375.1786, "underlyingValue": 1009.6, "category": "Slide-in-OI-Slide", "type": "SS", "abs_pChange": 0.69, "volume_score": "Medium"}, {"symbol": "BEL", "instrument": "Stock Futures", "instrumentType": "FUTSTK", "expiryDate": "30-Dec-2025", "ltp": 388.1, "prevClose": 391.0, "pChange": -0.74, "latestOI": 75030, "prevOI": 76688, "changeInOI": -1658, "pChangeInOI": -2.16, "volume": 8266, "turnover": 45846.41841, "underlyingValue": 386.9, "category": "Slide-in-OI-Slide", "type": "SS", "abs_pChange": 0.74, "volume_score": "Medium"}, {"symbol": "IDEA", "instrument": "Stock Futures", "instrumentType": "FUTSTK", "expiryDate": "30-Dec-2025", "ltp": 10.76, "prevClose": 10.79, "pChange": -0.28, "latestOI": 84571, "prevOI": 85827, "changeInOI": -1256, "pChangeInOI": -1.46, "volume": 9756, "turnover": 75797.60787, "underlyingValue": 10.71, "category": "Slide-in-OI-Slide", "type": "SS", "abs_pChange": 0.28, "volume_score": "High"}, {"symbol": "KAYNES", "instrument": "Stock Futures", "instrumentType": "FUTSTK", "expiryDate": "30-Dec-2025", "ltp": 3885.0, "prevClose": 4366.0, "pChange": -11.02, "latestOI": 33216, "prevOI": 34450, "changeInOI": -1234, "pChangeInOI": -3.58, "volume": 43524, "turnover": 179253.15876, "underlyingValue": 3876.0, "category": "Slide-in-OI-Slide", "type": "SS", "abs_pChange": 11.02, "volume_score": "Very High"}, {"symbol": "LT", "instrument": "Stock Futures", "instrumentType": "FUTSTK", "expiryDate": "30-Dec-2025", "ltp": 4007.0, "prevClose": 4009.0, "pChange": -0.05, "latestOI": 72977, "prevOI": 74177, "changeInOI": -1200, "pChangeInOI": -1.62, "volume": 6254, "turnover": 43969.20041, "underlyingValue": 3990.6, "category": "Slide-in-OI-Slide", "type": "SS", "abs_pChange": 0.05, "volume_score": "Medium"}, {"symbol": "KOTAKBANK", "instrument": "Stock Futures", "instrumentType": "FUTSTK", "expiryDate": "30-Dec-2025", "ltp": 2133.9, "prevClose": 2134.6, "pChange": -0.03, "latestOI": 92712, "prevOI": 93782, "changeInOI": -1070, "pChangeInOI": -1.14, "volume": 7644, "turnover": 65550.66336, "underlyingValue": 2128.0, "category": "Slide-in-OI-Slide", "type": "SS", "abs_pChange": 0.03, "volume_score": "Medium"}, {"symbol": "POLICYBZR", "instrument": "Stock Futures", "instrumentType": "FUTSTK", "expiryDate": "30-Dec-2025", "ltp": 1926.5, "prevClose": 1962.2, "pChange": -1.82, "latestOI": 17781, "prevOI": 18783, "changeInOI": -1002, "pChangeInOI": -5.33, "volume": 3656, "turnover": 24718.0332, "underlyingValue": 1921.0, "category": "Slide-in-OI-Slide", "type": "SS", "abs_pChange": 1.82, "volume_score": "Low"}, {"symbol": "TITAN", "instrument": "Stock Futures", "instrumentType": "FUTSTK", "expiryDate": "30-Dec-2025", "ltp": 3837.0, "prevClose": 3859.2, "pChange": -0.58, "latestOI": 52126, "prevOI": 53070, "changeInOI": -944, "pChangeInOI": -1.78, "volume": 3551, "turnover": 23935.61315, "underlyingValue": 3830.4, "category": "Slide-in-OI-Slide", "type": "SS", "abs_pChange": 0.58, "volume_score": "Low"}, {"symbol": "CGPOWER", "instrument": "Stock Futures", "instrumentType": "FUTSTK", "expiryDate": "30-Dec-2025", "ltp": 666.35, "prevClose": 669.5, "pChange": -0.47, "latestOI": 17480, "prevOI": 18362, "changeInOI": -882, "pChangeInOI": -4.8, "volume": 3468, "turnover": 19848.12696, "underlyingValue": 664.05, "category": "Slide-in-OI-Slide", "type": "SS", "abs_pChange": 0.47, "volume_score": "Low"}, {"symbol": "RELIANCE", "instrument": "Stock Futures", "instrumentType": "FUTSTK", "expiryDate": "30-Dec-2025", "ltp": 1539.1, "prevClose": 1533.5, "pChange": 0.37, "latestOI": 191449, "prevOI": 197299, "changeInOI": -5850, "pChangeInOI": -2.97, "volume": 16417, "turnover": 126735.13575, "underlyingValue": 1533.5, "category": "Slide-in-OI-Rise", "type": "SR", "abs_pChange": 0.37, "volume_score": "Very High"}, {"symbol": "HINDALCO", "instrument": "Stock Futures", "instrumentType": "FUTSTK", "expiryDate": "30-Dec-2025", "ltp": 824.2, "prevClose": 814.85, "pChange": 1.15, "latestOI": 110452, "prevOI": 113053, "changeInOI": -2601, "pChangeInOI": -2.3, "volume": 10546, "turnover": 61003.54792, "underlyingValue": 821.6, "category": "Slide-in-OI-Rise", "type": "SR", "abs_pChange": 1.15, "volume_score": "Very High"}, {"symbol": "VEDL", "instrument": "Stock Futures", "instrumentType": "FUTSTK", "expiryDate": "30-Dec-2025", "ltp": 524.8, "prevClose": 517.5, "pChange": 1.41, "latestOI": 92311, "prevOI": 94029, "changeInOI": -1718, "pChangeInOI": -1.83, "volume": 17232, "turnover": 103962.89616, "underlyingValue": 524.25, "category": "Slide-in-OI-Rise", "type": "SR", "abs_pChange": 1.41, "volume_score": "Very High"}, {"symbol": "COALINDIA", "instrument": "Stock Futures", "instrumentType": "FUTSTK", "expiryDate": "30-Dec-2025", "ltp": 383.4, "prevClose": 380.1, "pChange": 0.87, "latestOI": 37991, "prevOI": 39486, "changeInOI": -1495, "pChangeInOI": -3.79, "volume": 7399, "turnover": 38202.59079, "underlyingValue": 381.8, "category": "Slide-in-OI-Rise", "type": "SR", "abs_pChange": 0.87, "volume_score": "Medium"}, {"symbol": "HINDZINC", "instrument": "Stock Futures", "instrumentType": "FUTSTK", "expiryDate": "30-Dec-2025", "ltp": 512.65, "prevClose": 493.75, "pChange": 3.83, "latestOI": 26704, "prevOI": 28061, "changeInOI": -1357, "pChangeInOI": -4.84, "volume": 16431, "turnover": 103236.38377, "underlyingValue": 512.1, "category": "Slide-in-OI-Rise", "type": "SR", "abs_pChange": 3.83, "volume_score": "Very High"}, {"symbol": "GRASIM", "instrument": "Stock Futures", "instrumentType": "FUTSTK", "expiryDate": "30-Dec-2025", "ltp": 2757.5, "prevClose": 2755.7, "pChange": 0.07, "latestOI": 63272, "prevOI": 64616, "changeInOI": -1344, "pChangeInOI": -2.08, "volume": 5224, "turnover": 36146.162, "underlyingValue": 2748.0, "category": "Slide-in-OI-Rise", "type": "SR", "abs_pChange": 0.07, "volume_score": "Low"}, {"symbol": "HDFCAMC", "instrument": "Stock Futures", "instrumentType": "FUTSTK", "expiryDate": "30-Dec-2025", "ltp": 2615.9, "prevClose": 2572.1, "pChange": 1.7, "latestOI": 15323, "prevOI": 16602, "changeInOI": -1279, "pChangeInOI": -7.7, "volume": 4541, "turnover": 35646.35049, "underlyingValue": 2608.1, "category": "Slide-in-OI-Rise", "type": "SR", "abs_pChange": 1.7, "volume_score": "Low"}, {"symbol": "ITC", "instrument": "Stock Futures", "instrumentType": "FUTSTK", "expiryDate": "30-Dec-2025", "ltp": 404.25, "prevClose": 402.85, "pChange": 0.35, "latestOI": 100163, "prevOI": 101152, "changeInOI": -989, "pChangeInOI": -0.98, "volume": 3695, "turnover": 23904.5808, "underlyingValue": 403.05, "category": "Slide-in-OI-Rise", "type": "SR", "abs_pChange": 0.35, "volume_score": "Low"}]