[{"symbol": "NIFTY", "instrument": "Index Futures", "instrumentType": "FUTIDX", "expiryDate": "30-Sep-2025", "ltp": 24815.6, "prevClose": 24689.9, "pChange": 0.51, "latestOI": 124736, "prevOI": 129226, "changeInOI": -4490, "pChangeInOI": -3.47, "volume": 26897, "turnover": 500040.10972, "underlyingValue": 24761.5, "category": "Slide-in-OI-Rise", "type": "SR", "abs_pChange": 0.51, "volume_score": "Very High"}, {"symbol": "TCS", "instrument": "Stock Futures", "instrumentType": "FUTSTK", "expiryDate": "30-Sep-2025", "ltp": 2931.0, "prevClose": 2903.8, "pChange": 0.94, "latestOI": 57123, "prevOI": 59999, "changeInOI": -2876, "pChangeInOI": -4.79, "volume": 9764, "turnover": 49961.70452, "underlyingValue": 2925.5, "category": "Slide-in-OI-Rise", "type": "SR", "abs_pChange": 0.94, "volume_score": "High"}, {"symbol": "BANKNIFTY", "instrument": "Index Futures", "instrumentType": "FUTIDX", "expiryDate": "30-Sep-2025", "ltp": 54736.2, "prevClose": 54474.8, "pChange": 0.48, "latestOI": 39462, "prevOI": 41355, "changeInOI": -1893, "pChangeInOI": -4.58, "volume": 9483, "turnover": 181444.43139, "underlyingValue": 54613.3, "category": "Slide-in-OI-Rise", "type": "SR", "abs_pChange": 0.48, "volume_score": "High"}, {"symbol": "PATANJALI", "instrument": "Stock Futures", "instrumentType": "FUTSTK", "expiryDate": "30-Sep-2025", "ltp": 601.0, "prevClose": 590.8, "pChange": 1.73, "latestOI": 10732, "prevOI": 12324, "changeInOI": -1592, "pChangeInOI": -12.92, "volume": 2738, "turnover": 14770.66122, "underlyingValue": 600.1, "category": "Slide-in-OI-Rise", "type": "SR", "abs_pChange": 1.73, "volume_score": "Low"}, {"symbol": "TATAMOTORS", "instrument": "Stock Futures", "instrumentType": "FUTSTK", "expiryDate": "30-Sep-2025", "ltp": 675.55, "prevClose": 673.05, "pChange": 0.37, "latestOI": 49376, "prevOI": 50679, "changeInOI": -1303, "pChangeInOI": -2.57, "volume": 7081, "turnover": 38357.49376, "underlyingValue": 675.5, "category": "Slide-in-OI-Rise", "type": "SR", "abs_pChange": 0.37, "volume_score": "Medium"}, {"symbol": "HCLTECH", "instrument": "Stock Futures", "instrumentType": "FUTSTK", "expiryDate": "30-Sep-2025", "ltp": 1395.7, "prevClose": 1394.4, "pChange": 0.09, "latestOI": 22116, "prevOI": 23383, "changeInOI": -1267, "pChangeInOI": -5.42, "volume": 5823, "turnover": 28468.29762, "underlyingValue": 1392.5, "category": "Slide-in-OI-Rise", "type": "SR", "abs_pChange": 0.09, "volume_score": "Medium"}, {"symbol": "BSE", "instrument": "Stock Futures", "instrumentType": "FUTSTK", "expiryDate": "30-Sep-2025", "ltp": 2111.1, "prevClose": 2050.1, "pChange": 2.98, "latestOI": 15186, "prevOI": 16387, "changeInOI": -1201, "pChangeInOI": -7.33, "volume": 5442, "turnover": 42741.468, "underlyingValue": 2107.8, "category": "Slide-in-OI-Rise", "type": "SR", "abs_pChange": 2.98, "volume_score": "Medium"}, {"symbol": "BAJFINANCE", "instrument": "Stock Futures", "instrumentType": "FUTSTK", "expiryDate": "30-Sep-2025", "ltp": 990.3, "prevClose": 986.7, "pChange": 0.36, "latestOI": 25670, "prevOI": 26865, "changeInOI": -1195, "pChangeInOI": -4.45, "volume": 6984, "turnover": 52033.7682, "underlyingValue": 989.75, "category": "Slide-in-OI-Rise", "type": "SR", "abs_pChange": 0.36, "volume_score": "Medium"}, {"symbol": "DRREDDY", "instrument": "Stock Futures", "instrumentType": "FUTSTK", "expiryDate": "30-Sep-2025", "ltp": 1258.8, "prevClose": 1252.8, "pChange": 0.48, "latestOI": 8180, "prevOI": 9343, "changeInOI": -1163, "pChangeInOI": -12.45, "volume": 3882, "turnover": 30601.07812, "underlyingValue": 1256.5, "category": "Slide-in-OI-Rise", "type": "SR", "abs_pChange": 0.48, "volume_score": "Low"}, {"symbol": "UNIONBANK", "instrument": "Stock Futures", "instrumentType": "FUTSTK", "expiryDate": "30-Sep-2025", "ltp": 136.69, "prevClose": 134.19, "pChange": 1.86, "latestOI": 5560, "prevOI": 6634, "changeInOI": -1074, "pChangeInOI": -16.19, "volume": 2205, "turnover": 13218.95295, "underlyingValue": 136.46, "category": "Slide-in-OI-Rise", "type": "SR", "abs_pChange": 1.86, "volume_score": "Low"}, {"symbol": "IDEA", "instrument": "Stock Futures", "instrumentType": "FUTSTK", "expiryDate": "30-Sep-2025", "ltp": 8.19, "prevClose": 8.03, "pChange": 1.99, "latestOI": 29803, "prevOI": 30812, "changeInOI": -1009, "pChangeInOI": -3.27, "volume": 5272, "turnover": 30635.15706, "underlyingValue": 8.19, "category": "Slide-in-OI-Rise", "type": "SR", "abs_pChange": 1.99, "volume_score": "Low"}, {"symbol": "INDUSINDBK", "instrument": "Stock Futures", "instrumentType": "FUTSTK", "expiryDate": "30-Sep-2025", "ltp": 728.45, "prevClose": 712.85, "pChange": 2.19, "latestOI": 26632, "prevOI": 27590, "changeInOI": -958, "pChangeInOI": -3.47, "volume": 6149, "turnover": 31126.54545, "underlyingValue": 726.85, "category": "Slide-in-OI-Rise", "type": "SR", "abs_pChange": 2.19, "volume_score": "Medium"}, {"symbol": "BANDHANBNK", "instrument": "Stock Futures", "instrumentType": "FUTSTK", "expiryDate": "30-Sep-2025", "ltp": 159.59, "prevClose": 155.42, "pChange": 2.68, "latestOI": 7562, "prevOI": 8470, "changeInOI": -908, "pChangeInOI": -10.72, "volume": 1850, "turnover": 10580.742, "underlyingValue": 159.05, "category": "Slide-in-OI-Rise", "type": "SR", "abs_pChange": 2.68, "volume_score": "Low"}, {"symbol": "IRFC", "instrument": "Stock Futures", "instrumentType": "FUTSTK", "expiryDate": "30-Sep-2025", "ltp": 124.2, "prevClose": 121.95, "pChange": 1.85, "latestOI": 3728, "prevOI": 4594, "changeInOI": -866, "pChangeInOI": -18.85, "volume": 1251, "turnover": 6591.17497, "underlyingValue": 123.88, "category": "Slide-in-OI-Rise", "type": "SR", "abs_pChange": 1.85, "volume_score": "Low"}, {"symbol": "CDSL", "instrument": "Stock Futures", "instrumentType": "FUTSTK", "expiryDate": "30-Sep-2025", "ltp": 1495.0, "prevClose": 1469.7, "pChange": 1.72, "latestOI": 6083, "prevOI": 6927, "changeInOI": -844, "pChangeInOI": -12.18, "volume": 2548, "turnover": 18009.74812, "underlyingValue": 1492.0, "category": "Slide-in-OI-Rise", "type": "SR", "abs_pChange": 1.72, "volume_score": "Low"}, {"symbol": "RELIANCE", "instrument": "Stock Futures", "instrumentType": "FUTSTK", "expiryDate": "28-Oct-2025", "ltp": 1391.5, "prevClose": 1383.7, "pChange": 0.56, "latestOI": 195864, "prevOI": 183694, "changeInOI": 12170, "pChangeInOI": 6.63, "volume": 15258, "turnover": 106212.4638, "underlyingValue": 1384.0, "category": "Rise-in-OI-Rise", "type": "RR", "abs_pChange": 0.56, "volume_score": "Very High"}, {"symbol": "NIFTY", "instrument": "Index Futures", "instrumentType": "FUTIDX", "expiryDate": "28-Oct-2025", "ltp": 24937.4, "prevClose": 24812.0, "pChange": 0.51, "latestOI": 140855, "prevOI": 130242, "changeInOI": 10613, "pChangeInOI": 8.15, "volume": 20707, "turnover": 386822.96322, "underlyingValue": 24761.5, "category": "Rise-in-OI-Rise", "type": "RR", "abs_pChange": 0.51, "volume_score": "Very High"}, {"symbol": "JSWSTEEL", "instrument": "Stock Futures", "instrumentType": "FUTSTK", "expiryDate": "28-Oct-2025", "ltp": 1146.3, "prevClose": 1138.9, "pChange": 0.65, "latestOI": 54931, "prevOI": 44645, "changeInOI": 10286, "pChangeInOI": 23.04, "volume": 11157, "turnover": 86145.31683, "underlyingValue": 1140.0, "category": "Rise-in-OI-Rise", "type": "RR", "abs_pChange": 0.65, "volume_score": "High"}, {"symbol": "ICICIBANK", "instrument": "Stock Futures", "instrumentType": "FUTSTK", "expiryDate": "28-Oct-2025", "ltp": 1370.3, "prevClose": 1369.2, "pChange": 0.08, "latestOI": 128099, "prevOI": 118806, "changeInOI": 9293, "pChangeInOI": 7.82, "volume": 11848, "turnover": 113815.56088, "underlyingValue": 1360.4, "category": "Rise-in-OI-Rise", "type": "RR", "abs_pChange": 0.08, "volume_score": "Very High"}, {"symbol": "HDFCBANK", "instrument": "Stock Futures", "instrumentType": "FUTSTK", "expiryDate": "28-Oct-2025", "ltp": 958.75, "prevClose": 951.5, "pChange": 0.76, "latestOI": 159382, "prevOI": 150825, "changeInOI": 8557, "pChangeInOI": 5.67, "volume": 12139, "turnover": 127663.07103, "underlyingValue": 951.85, "category": "Rise-in-OI-Rise", "type": "RR", "abs_pChange": 0.76, "volume_score": "Very High"}, {"symbol": "SAMMAANCAP", "instrument": "Stock Futures", "instrumentType": "FUTSTK", "expiryDate": "28-Oct-2025", "ltp": 149.45, "prevClose": 138.36, "pChange": 8.02, "latestOI": 16006, "prevOI": 7677, "changeInOI": 8329, "pChangeInOI": 108.49, "volume": 15423, "turnover": 98602.94052, "underlyingValue": 148.3, "category": "Rise-in-OI-Rise", "type": "RR", "abs_pChange": 8.02, "volume_score": "Very High"}, {"symbol": "INFY", "instrument": "Stock Futures", "instrumentType": "FUTSTK", "expiryDate": "28-Oct-2025", "ltp": 1457.3, "prevClose": 1446.7, "pChange": 0.73, "latestOI": 77856, "prevOI": 69646, "changeInOI": 8210, "pChangeInOI": 11.79, "volume": 11714, "turnover": 68339.94456, "underlyingValue": 1460.3, "category": "Rise-in-OI-Rise", "type": "RR", "abs_pChange": 0.73, "volume_score": "Very High"}, {"symbol": "TCS", "instrument": "Stock Futures", "instrumentType": "FUTSTK", "expiryDate": "28-Oct-2025", "ltp": 2934.9, "prevClose": 2907.6, "pChange": 0.94, "latestOI": 121702, "prevOI": 114456, "changeInOI": 7246, "pChangeInOI": 6.33, "volume": 11534, "turnover": 59078.21489, "underlyingValue": 2925.5, "category": "Rise-in-OI-Rise", "type": "RR", "abs_pChange": 0.94, "volume_score": "High"}, {"symbol": "BAJFINANCE", "instrument": "Stock Futures", "instrumentType": "FUTSTK", "expiryDate": "28-Oct-2025", "ltp": 995.3, "prevClose": 991.9, "pChange": 0.34, "latestOI": 97923, "prevOI": 91644, "changeInOI": 6279, "pChangeInOI": 6.85, "volume": 7952, "turnover": 59563.0644, "underlyingValue": 989.75, "category": "Rise-in-OI-Rise", "type": "RR", "abs_pChange": 0.34, "volume_score": "High"}, {"symbol": "KOTAKBANK", "instrument": "Stock Futures", "instrumentType": "FUTSTK", "expiryDate": "28-Oct-2025", "ltp": 2013.2, "prevClose": 2006.6, "pChange": 0.33, "latestOI": 70406, "prevOI": 64988, "changeInOI": 5418, "pChangeInOI": 8.34, "volume": 7357, "turnover": 59204.13324, "underlyingValue": 2000.5, "category": "Rise-in-OI-Rise", "type": "RR", "abs_pChange": 0.33, "volume_score": "High"}, {"symbol": "INFY", "instrument": "Stock Futures", "instrumentType": "FUTSTK", "expiryDate": "30-Sep-2025", "ltp": 1463.1, "prevClose": 1453.3, "pChange": 0.67, "latestOI": 67999, "prevOI": 62666, "changeInOI": 5333, "pChangeInOI": 8.51, "volume": 14631, "turnover": 85646.36256, "underlyingValue": 1460.3, "category": "Rise-in-OI-Rise", "type": "RR", "abs_pChange": 0.67, "volume_score": "Very High"}, {"symbol": "BHARTIARTL", "instrument": "Stock Futures", "instrumentType": "FUTSTK", "expiryDate": "28-Oct-2025", "ltp": 1927.4, "prevClose": 1924.8, "pChange": 0.14, "latestOI": 66841, "prevOI": 61518, "changeInOI": 5323, "pChangeInOI": 8.65, "volume": 6410, "turnover": 58553.28277, "underlyingValue": 1914.4, "category": "Rise-in-OI-Rise", "type": "RR", "abs_pChange": 0.14, "volume_score": "Medium"}, {"symbol": "SBIN", "instrument": "Stock Futures", "instrumentType": "FUTSTK", "expiryDate": "28-Oct-2025", "ltp": 868.15, "prevClose": 860.8, "pChange": 0.85, "latestOI": 100645, "prevOI": 95607, "changeInOI": 5038, "pChangeInOI": 5.27, "volume": 7894, "turnover": 51350.8647, "underlyingValue": 863.2, "category": "Rise-in-OI-Rise", "type": "RR", "abs_pChange": 0.85, "volume_score": "High"}, {"symbol": "RECLTD", "instrument": "Stock Futures", "instrumentType": "FUTSTK", "expiryDate": "28-Oct-2025", "ltp": 374.4, "prevClose": 369.3, "pChange": 1.38, "latestOI": 35776, "prevOI": 31097, "changeInOI": 4679, "pChangeInOI": 15.05, "volume": 6132, "turnover": 29184.93207, "underlyingValue": 371.65, "category": "Rise-in-OI-Rise", "type": "RR", "abs_pChange": 1.38, "volume_score": "Medium"}, {"symbol": "INDUSINDBK", "instrument": "Stock Futures", "instrumentType": "FUTSTK", "expiryDate": "28-Oct-2025", "ltp": 731.9, "prevClose": 715.4, "pChange": 2.31, "latestOI": 57771, "prevOI": 53565, "changeInOI": 4206, "pChangeInOI": 7.85, "volume": 7689, "turnover": 39116.40348, "underlyingValue": 726.85, "category": "Rise-in-OI-Rise", "type": "RR", "abs_pChange": 2.31, "volume_score": "High"}, {"symbol": "HCLTECH", "instrument": "Stock Futures", "instrumentType": "FUTSTK", "expiryDate": "28-Oct-2025", "ltp": 1390.7, "prevClose": 1389.8, "pChange": 0.06, "latestOI": 37438, "prevOI": 33395, "changeInOI": 4043, "pChangeInOI": 12.11, "volume": 6845, "turnover": 33338.77785, "underlyingValue": 1392.5, "category": "Rise-in-OI-Rise", "type": "RR", "abs_pChange": 0.06, "volume_score": "Medium"}, {"symbol": "JSWENERGY", "instrument": "Stock Futures", "instrumentType": "FUTSTK", "expiryDate": "28-Oct-2025", "ltp": 532.6, "prevClose": 523.7, "pChange": 1.7, "latestOI": 30007, "prevOI": 26062, "changeInOI": 3945, "pChangeInOI": 15.14, "volume": 4889, "turnover": 26030.0138, "underlyingValue": 528.1, "category": "Rise-in-OI-Rise", "type": "RR", "abs_pChange": 1.7, "volume_score": "Low"}]